nav_spec/__init__.py
nav_spec/context_processors.py
nav_spec/py.typed
nav_spec/templatetags/__init__.py
nav_spec/templatetags/nav_spec.py
django_nav_spec-1.0.0.dist-info/METADATA
django_nav_spec-1.0.0.dist-info/WHEEL
django_nav_spec-1.0.0.dist-info/licenses/LICENSE
django_nav_spec-1.0.0.dist-info/RECORD
