Metadata-Version: 2.4
Name: django-nav-spec
Version: 1.0.0
Summary: Define your navigation in settings and simplify your templates.
Project-URL: Homepage, https://github.com/benbacardi/django-nav-spec
Project-URL: Repository, https://github.com/benbacardi/django-nav-spec
Project-URL: Issues, https://github.com/benbacardi/django-nav-spec/issues
Author-email: Ben Cardy <me@bencardy.co.uk>
License: MIT
License-File: LICENSE
Keywords: django,menu,nav,navigation
Classifier: Framework :: Django
Classifier: Framework :: Django :: 4.2
Classifier: Framework :: Django :: 5.0
Classifier: Framework :: Django :: 5.1
Classifier: Framework :: Django :: 5.2
Classifier: Framework :: Django :: 6.0
Classifier: License :: OSI Approved :: MIT License
Classifier: Programming Language :: Python :: 3
Classifier: Programming Language :: Python :: 3.10
Classifier: Programming Language :: Python :: 3.11
Classifier: Programming Language :: Python :: 3.12
Classifier: Programming Language :: Python :: 3.13
Requires-Python: >=3.10
Requires-Dist: django>=4.2
